telebot/__init__.py
telebot/apihelper.py
telebot/async_telebot.py
telebot/asyncio_filters.py
telebot/asyncio_handler_backends.py
telebot/asyncio_helper.py
telebot/callback_data.py
telebot/custom_filters.py
telebot/formatting.py
telebot/handler_backends.py
telebot/service_utils.py
telebot/types.py
telebot/util.py
telebot/version.py
telebot/asyncio_storage/__init__.py
telebot/asyncio_storage/base_storage.py
telebot/asyncio_storage/memory_storage.py
telebot/asyncio_storage/pickle_storage.py
telebot/asyncio_storage/redis_storage.py
telebot/ext/__init__.py
telebot/ext/reloader.py
telebot/ext/aio/__init__.py
telebot/ext/aio/webhooks.py
telebot/ext/sync/__init__.py
telebot/ext/sync/webhooks.py
telebot/states/__init__.py
telebot/states/asyncio/__init__.py
telebot/states/asyncio/context.py
telebot/states/asyncio/middleware.py
telebot/states/sync/__init__.py
telebot/states/sync/context.py
telebot/states/sync/middleware.py
telebot/storage/__init__.py
telebot/storage/base_storage.py
telebot/storage/memory_storage.py
telebot/storage/pickle_storage.py
telebot/storage/redis_storage.py
telegram_bale_bot-4.27.0.dist-info/METADATA
telegram_bale_bot-4.27.0.dist-info/WHEEL
telegram_bale_bot-4.27.0.dist-info/licenses/LICENSE
telegram_bale_bot-4.27.0.dist-info/RECORD
