Metadata-Version: 2.4
Name: telegram-bale-bot
Version: 4.27.0
Summary: A simple and easy-to-use library for creating Telegram bots and Bale messenger bots, forked from pyTelegramBotAPI
Project-URL: Homepage, https://github.com/mahdikiani/telegram-bale-bot
Project-URL: OriginalPackage, https://github.com/eternnoir/pyTelegramBotAPI
Project-URL: Documentation, https://pytba.readthedocs.org
Project-URL: Repository, https://github.com/eternnoir/pyTelegramBotAPI
Project-URL: Issues, https://github.com/eternnoir/pyTelegramBotAPI/issues
Author-email: Mahdi Kiani <mahdikiany@gmail.com>
License: GPL2
License-File: LICENSE
Keywords: api,bot,telegram,tools
Classifier: Development Status :: 5 - Production/Stable
Classifier: Environment :: Console
Classifier: License :: OSI Approved :: GNU General Public License v2 (GPLv2)
Classifier: Programming Language :: Python :: 3
Classifier: Programming Language :: Python :: 3.9
Classifier: Programming Language :: Python :: 3.10
Classifier: Programming Language :: Python :: 3.11
Classifier: Programming Language :: Python :: 3.12
Classifier: Programming Language :: Python :: 3.13
Requires-Python: >=3.9
Requires-Dist: requests
Provides-Extra: aiohttp
Requires-Dist: aiohttp; extra == 'aiohttp'
Provides-Extra: coloredlogs
Requires-Dist: coloredlogs; extra == 'coloredlogs'
Provides-Extra: fastapi
Requires-Dist: fastapi; extra == 'fastapi'
Provides-Extra: json
Requires-Dist: ujson; extra == 'json'
Provides-Extra: pil
Requires-Dist: pillow; extra == 'pil'
Provides-Extra: psutil
Requires-Dist: psutil; extra == 'psutil'
Provides-Extra: redis
Requires-Dist: redis>=3.4.1; extra == 'redis'
Provides-Extra: uvicorn
Requires-Dist: uvicorn; extra == 'uvicorn'
Provides-Extra: watchdog
Requires-Dist: watchdog; extra == 'watchdog'
